test/__init__.py
test/test_tmt.py
topictuner/__init__.py
topictuner/basetuner.py
topictuner/cuml_topictuner.py
topictuner/topictuner.py
topicmodeltuner-0.3.4.dist-info/LICENSE
topicmodeltuner-0.3.4.dist-info/METADATA
topicmodeltuner-0.3.4.dist-info/WHEEL
topicmodeltuner-0.3.4.dist-info/top_level.txt
topicmodeltuner-0.3.4.dist-info/RECORD
