Metadata-Version: 2.1
Name: topicmodeltuner
Version: 0.3.4
Summary: HDBSCAN Tuning for BERTopic Models
Home-page: https://github.com/drob-xx/TopicTuner
Download-URL: https://github.com/drob-xx/TopicTuner/archive/refs/tags/0.3.4.tar.gz
Author: Dan Robinson
Author-email: drob707@gmail.com
Classifier: Programming Language :: Python :: 3
Classifier: License :: OSI Approved :: GNU General Public License v3 (GPLv3)
Classifier: Operating System :: OS Independent
Requires-Python: >=3
License-File: LICENSE
Requires-Dist: loguru
Requires-Dist: bertopic (>=v0.10.0)
